dotmagic/__init__.py
dotmagic/config.py
dotmagic/utils.py
dotmagic-0.1.1.dist-info/LICENSE
dotmagic-0.1.1.dist-info/METADATA
dotmagic-0.1.1.dist-info/WHEEL
dotmagic-0.1.1.dist-info/top_level.txt
dotmagic-0.1.1.dist-info/RECORD
