Metadata-Version: 2.1
Name: dotmagic
Version: 0.1.1
Summary: A Python library for accessing environment variables using dot notation.
Home-page: https://github.com/viperadnan-git/dotmagic
Download-URL: https://github.com/viperadnan-git/gdnan/archive/v0.1.1.tar.gz
Author: Adnan Ahmad
Author-email: viperadnan@gmail.com
License: GPLv3+
Keywords: environment,variables,dotenv,env,config,configuration
Classifier: Programming Language :: Python :: 3
Classifier: Programming Language :: Python :: 3.8
Classifier: Programming Language :: Python :: 3.9
Classifier: Programming Language :: Python :: 3.10
Classifier: Programming Language :: Python :: 3.11
Classifier: License :: OSI Approved :: GNU General Public License v3 or later (GPLv3+)
Classifier: Operating System :: OS Independent
Requires-Python: >=3.8
License-File: LICENSE
Requires-Dist: python-dotenv >=1.0.0
